geopedestrian/__init__.py
geopedestrian/categories.py
geopedestrian/services.py
geopedestrian/data/places-categories-2025.json
geopedestrian/data/places-categories.json
geopedestrian-0.3.dist-info/licenses/LICENSE
geopedestrian-0.3.dist-info/METADATA
geopedestrian-0.3.dist-info/WHEEL
geopedestrian-0.3.dist-info/top_level.txt
geopedestrian-0.3.dist-info/RECORD
