Metadata-Version: 2.4
Name: geopedestrian
Version: 0.3
Summary: Determines which locations are reachable by a pedestrian.
Project-URL: Homepage, https://geospatial-ai.de
Project-URL: GitHub, https://github.com/Geospatial-AI-DE/geopedestrian-py
Project-URL: Documentation, https://geopedestrian.readthedocs.io/en/latest
Keywords: geospatial,intelligence,urban,digital twin,walking,routing
Classifier: Programming Language :: Python :: 3
Classifier: License :: OSI Approved :: Apache Software License
Classifier: Operating System :: OS Independent
Requires-Python: >=3.7
License-File: LICENSE
Requires-Dist: georapid
Dynamic: license-file
